somali_number_converter/__init__.py
somali_number_converter/converter.py
somali_number_converter-0.0.1.dist-info/LICENSE
somali_number_converter-0.0.1.dist-info/METADATA
somali_number_converter-0.0.1.dist-info/WHEEL
somali_number_converter-0.0.1.dist-info/top_level.txt
somali_number_converter-0.0.1.dist-info/RECORD
