Metadata-Version: 2.2
Name: somali_number_converter
Version: 0.0.1
Summary: A package to convert numbers in PDFs to Somali words.
Home-page: https://github.com/abdoltd/somali_number_converter
Author: ABDOL
Author-email: abdoldevtra@gmail.com
License-File: LICENSE
Requires-Dist: pdfplumber
Dynamic: author
Dynamic: author-email
Dynamic: description
Dynamic: description-content-type
Dynamic: home-page
Dynamic: requires-dist
Dynamic: summary
